README.txt
setup.py
Products/__init__.py
Products.SecureMailHost.egg-info/PKG-INFO
Products.SecureMailHost.egg-info/SOURCES.txt
Products.SecureMailHost.egg-info/dependency_links.txt
Products.SecureMailHost.egg-info/namespace_packages.txt
Products.SecureMailHost.egg-info/not-zip-safe
Products.SecureMailHost.egg-info/requires.txt
Products.SecureMailHost.egg-info/top_level.txt
Products/SecureMailHost/HISTORY.txt
Products/SecureMailHost/SecureMailHost.py
Products/SecureMailHost/__init__.py
Products/SecureMailHost/config.py
Products/SecureMailHost/mail.py
Products/SecureMailHost/version.txt
Products/SecureMailHost/tests/__init__.py
Products/SecureMailHost/tests/common.py
Products/SecureMailHost/tests/framework.py
Products/SecureMailHost/tests/runalltests.py
Products/SecureMailHost/tests/test_headerparsing.py
Products/SecureMailHost/tests/test_messages.py
Products/SecureMailHost/tests/test_validateEmail.py
Products/SecureMailHost/tests/in/buergschaft.txt
Products/SecureMailHost/tests/in/loremipsum.txt
Products/SecureMailHost/tests/out/buergschaft.txt
Products/SecureMailHost/tests/out/buergschaft_latin1.txt
Products/SecureMailHost/tests/out/buergschaft_utf8.txt
Products/SecureMailHost/tests/out/buergschaft_utf8_to.txt
Products/SecureMailHost/tests/out/loremipsum.txt
Products/SecureMailHost/www/MailHost_icon.gif
Products/SecureMailHost/www/addMailHost_form.dtml
Products/SecureMailHost/www/manageMailHost.dtml
docs/LICENSE.txt
